{
  "success": true,
  "code": 200,
  "msg": "成功",
  "data": {
    "pageNo": 12,
    "total": 604,
    "pageSize": 10,
    "rows": [
      {
        "userId": 1,
        "userName": "张丽",
        "nickName": "装国识布西",
        "deptName": "表音角管",
        "roleName": "全眼进由",
        "descript": "次响红老位期断北管确复点规子写共因装铁得带下求。",
        "createTime": "1992-04-18 03:50:22"
      },
      {
        "userId": 2,
        "userName": "马军",
        "nickName": "按厂加重单",
        "deptName": "革前引活",
        "roleName": "向难矿直",
        "descript": "目向能律同型制相周强空体县近起矿类求海信见么存收运知马代它易手在流政果存法张断日与员体主般。",
        "createTime": "2019-09-26 05:48:29"
      },
      {
        "userId": 3,
        "userName": "李丽",
        "nickName": "府叫空水采",
        "deptName": "更经应代",
        "roleName": "例几农专",
        "descript": "四华体此际千国基整土何约然铁把采日百每程效建五约许验十算党广线养地复青规看并场和千主记却及。",
        "createTime": "2011-05-13 01:11:02"
      },
      {
        "userId": 4,
        "userName": "冯刚",
        "nickName": "商过际无江",
        "deptName": "治规质细",
        "roleName": "族样较采",
        "descript": "信走后干习长教教如阶地交展现精片技我话值导安明我极什才的化周十易值。",
        "createTime": "1973-07-04 03:17:13"
      },
      {
        "userId": 5,
        "userName": "袁娟",
        "nickName": "整规查约品",
        "deptName": "不八区受",
        "roleName": "万百家商",
        "descript": "越许叫对己加基他民红书开长节加道理列米叫风完电低支战养正周形支团心办价或别发马活员场段精八权图空。",
        "createTime": "2004-03-17 09:53:09"
      },
      {
        "userId": 6,
        "userName": "侯涛",
        "nickName": "则斗规具所",
        "deptName": "定种养志",
        "roleName": "切质她劳",
        "descript": "条引指的二表每我油住团他许外志书件济今行花包情改还政给展保际参极口老状儿管之党从水。",
        "createTime": "1996-07-14 04:40:28"
      },
      {
        "userId": 7,
        "userName": "武刚",
        "nickName": "况单平层称",
        "deptName": "必交方特",
        "roleName": "农更温基",
        "descript": "除准期导开至即与火正现社节情太法因后须我金共温运们类意铁红准采济酸好亲象。",
        "createTime": "2016-07-09 06:12:55"
      },
      {
        "userId": 8,
        "userName": "薛刚",
        "nickName": "非计也着极",
        "deptName": "劳效持何",
        "roleName": "完消点传",
        "descript": "标近状同先太领规方低教表处今以需器需改海多车和级持你共经起团。",
        "createTime": "1974-12-15 10:19:15"
      },
      {
        "userId": 9,
        "userName": "毛娟",
        "nickName": "万重切号容",
        "deptName": "养率了你",
        "roleName": "表报维儿",
        "descript": "集们并千它几温料深后构线情青带那放可严加议名第。",
        "createTime": "1982-03-09 02:06:34"
      },
      {
        "userId": 10,
        "userName": "杜秀英",
        "nickName": "事习深图思",
        "deptName": "后点去火",
        "roleName": "断化值院",
        "descript": "车较半便适制组间物外行二气料阶影办人府一老种况平生更强数石类造流表响原等系劳调看观没都四求。",
        "createTime": "2011-01-21 06:46:18"
      }
    ]
  }
}
